README.md
setup.py
PyDeployCLI.egg-info/PKG-INFO
PyDeployCLI.egg-info/SOURCES.txt
PyDeployCLI.egg-info/dependency_links.txt
PyDeployCLI.egg-info/entry_points.txt
PyDeployCLI.egg-info/requires.txt
PyDeployCLI.egg-info/top_level.txt
pydeploy/__init__.py
pydeploy/command.py
pydeploy/command_chain.py
pydeploy/config.py
pydeploy/main.py
pydeploy/util.py
pydeploy/webhook.py
pydeploy/notifier/__init__.py
pydeploy/notifier/base.py
pydeploy/notifier/discord.py
pydeploy/notifier/factory.py
pydeploy/notifier/slack.py
pydeploy/tests/__init__.py
pydeploy/tests/test_command.py
pydeploy/tests/test_command_chain.py
pydeploy/tests/test_notifier.py
pydeploy/tests/test_webhook.py