Metadata-Version: 2.1
Name: PyDeployCLI
Version: 0.0.1
Summary: Automatically deploy git repositories
Home-page: https://github.com/yukinotenshi/pydeploy
Author: yukinotenshi
Author-email: gabriel.bentara@gmail.com
License: MIT
Keywords: automatic deploy deployment auto pull git
Platform: UNKNOWN
